tuze_setup_sample/__init__.py
tuze_setup_sample/col_package/__init__.py
tuze_setup_sample/col_package/col.py
tuze_setup_sample/str_package/__init__.py
tuze_setup_sample/str_package/str.py
tuze_setup_sample-1.0.0.dist-info/LICENSE
tuze_setup_sample-1.0.0.dist-info/METADATA
tuze_setup_sample-1.0.0.dist-info/WHEEL
tuze_setup_sample-1.0.0.dist-info/top_level.txt
tuze_setup_sample-1.0.0.dist-info/RECORD
