Metadata-Version: 2.1
Name: tuze_setup_sample
Version: 1.0.0
Summary: A useful tool package
Home-page: https://github.com/sharkshore/python-base-sample
Author: tuze
Author-email: tuze <sharkshore@163.com>
License: MIT
Project-URL: Homepage, https://github.com/sharkshore/python-base-sample
Classifier: Programming Language :: Python :: 3
Classifier: License :: OSI Approved :: MIT License
Classifier: Operating System :: OS Independent
Requires-Python: >=3.6
License-File: LICENSE
Requires-Dist: requests
Requires-Dist: colorama
